request_position/__init__.py
request_position/apps.py
request_position/helpers.py
request_position/middleware.py
request_position/settings.py
django_request_position-1.0.0.dist-info/LICENSE
django_request_position-1.0.0.dist-info/WHEEL
django_request_position-1.0.0.dist-info/METADATA
django_request_position-1.0.0.dist-info/RECORD
