Metadata-Version: 2.1
Name: django-request-position
Version: 1.0.0
Summary: Django app to add a 'position' field to the request, using GeoIP or GPS data given in the request headers.
Home-page: https://github.com/marcosgabarda/django-request-position
License: MIT
Author: Marcos Gabarda
Author-email: hey@marcosgabarda.com
Requires-Python: >=3.7,<4.0
Classifier: Environment :: Web Environment
Classifier: Framework :: Django
Classifier: Intended Audience :: Developers
Classifier: License :: OSI Approved :: MIT License
Classifier: Operating System :: OS Independent
Classifier: Programming Language :: Python
Classifier: Programming Language :: Python :: 3
Classifier: Programming Language :: Python :: 3.7
Classifier: Programming Language :: Python :: 3.8
Classifier: Programming Language :: Python :: 3.9
Classifier: Topic :: Utilities
Requires-Dist: django (>=3.0.0,<4.0.0)
Requires-Dist: geoip2 (>=4.3.0,<5.0.0)
